{
  "assuntos": [
    {
      "id": 1,
      "titulo": "Alexandre de Moraes amplia investigações sobre plataformas digitais",
      "data_evento": "2025-09-30",
      "data_iso": "2025-09-30T12:00:00.000Z",
      "categoria": "lawfare",
      "tags": ["lawfare", "stf", "censura", "alexandre-de-moraes", "plataformas", "big-techs"],
      "descricao": "Moraes ordena coleta compulsória de dados das principais plataformas para inquérito sobre disseminação de fake news.",
      "relevancia": "alta",
      "fontes": [
        "https://www.conjur.com.br/2025/09/30/moraes-amplia-investigacoes-plataformas",
        "https://www.gazetadopovo.com.br/politica/inquerito-fake-news-novas-ordens/"
      ],
      "pessoas_envolvidas": ["Alexandre de Moraes"],
      "instituicoes_envolvidas": ["STF"],
      "pais": "Brasil",
      "prioridade": 1
    },
    {
      "id": 2,
      "titulo": "EUA incluem ministros do STF e TSE em nova rodada de sanções",
      "data_evento": "2025-10-10",
      "data_iso": "2025-10-10T09:30:00.000Z",
      "categoria": "crise-diplomatica",
      "tags": ["crise-diplomatica", "stf", "tse", "secao301", "soberania", "usaid"],
      "descricao": "Governo norte-americano suspende vistos de ministros por suposta colaboração em censura digital e abuso de poder.",
      "relevancia": "alta",
      "fontes": [
        "https://oglobo.globo.com/mundo/eua-sanções-ministros-stf-tse-2025/",
        "https://www.estadao.com.br/internacional/sancoes-eua-stf-tse/"
      ],
      "pessoas_envolvidas": ["Alexandre de Moraes", "Edson Fachin"],
      "instituicoes_envolvidas": ["STF", "TSE", "Departamento de Estado dos EUA"],
      "pais": "Brasil",
      "prioridade": 2
    },
    {
      "id": 3,
      "titulo": "Polícia Federal realiza operação contra facções ligadas à lavagem de dinheiro",
      "data_evento": "2025-10-17",
      "data_iso": "2025-10-17T07:00:00.000Z",
      "categoria": "operacoes",
      "tags": ["operacoes", "coaf", "faccoes-criminosas", "lavagem-de-dinheiro", "seguranca-publica", "crime-organizado"],
      "descricao": "PF desmonta esquema nacional de lavagem envolvendo facções e empresários com prejuízo milionário.",
      "relevancia": "alta",
      "fontes": [
        "https://g1.globo.com/pf-operacao-lavagem-faccoes-2025/",
        "https://www.uol.com.br/noticias/pf-2025-faccoes-lavagem"
      ],
      "pessoas_envolvidas": ["Diretor da PF"],
      "instituicoes_envolvidas": ["PF", "COAF"],
      "pais": "Brasil",
      "prioridade": 3
    },
    {
      "id": 4,
      "titulo": "TSE aprova nova regulamentação de conteúdo eleitoral nas redes sociais",
      "data_evento": "2025-10-21",
      "data_iso": "2025-10-21T16:10:00.000Z",
      "categoria": "tse",
      "tags": ["tse", "censura", "plataformas", "eleições", "big-techs", "liberdade de expressão"],
      "descricao": "TSE estabelece regramento para remoção rápida de conteúdos considerados eleitorais irregulares das plataformas.",
      "relevancia": "alta",
      "fontes": [
        "https://www.tse.jus.br/noticias-tse/tse-regras-eleicoes-redes-2025",
        "https://www.terra.com.br/noticias/tse-remocao-plataformas"
      ],
      "pessoas_envolvidas": ["Ministro Cármen Lúcia"],
      "instituicoes_envolvidas": ["TSE"],
      "pais": "Brasil",
      "prioridade": 3
    },
    {
      "id": 5,
      "titulo": "Novo dossiê aponta venda de sentenças em tribunal federal",
      "data_evento": "2025-10-25",
      "data_iso": "2025-10-25T13:40:00.000Z",
      "categoria": "justica",
      "tags": ["justica", "corrupcao", "vazatoga", "dossie", "escandalos", "decisao-judicial"],
      "descricao": "Investigação revela grupo de magistrados envolvidos na comercialização de decisões judiciais em processos cíveis.",
      "relevancia": "alta",
      "fontes": [
        "https://noticias.uol.com.br/ultimas/venda-de-sentencas-dossie-2025/",
        "https://www.conjur.com.br/2025/10/25/dossie-magistrados-corrupcao"
      ],
      "pessoas_envolvidas": ["Juiz Federal Marcelo Lima"],
      "instituicoes_envolvidas": ["TRF", "Ministério Público"],
      "pais": "Brasil",
      "prioridade": 2
    },
    {
      "id": 6,
      "titulo": "Alexandre de Moraes solicita novos relatórios financeiros ao COAF",
      "data_evento": "2025-10-31",
      "data_iso": "2025-10-31T19:00:00.000Z",
      "categoria": "stf",
      "tags": ["stf", "coaf", "relatorios-financeiros", "alexandre-de-moraes", "lawfare"],
      "descricao": "STF amplia escopo de cooperação financeira em investigações contra figuras da oposição, gerando polêmica sobre legalidade.",
      "relevancia": "alta",
      "fontes": [
        "https://www.conjur.com.br/2025/10/31/stf-coaf-relatorios",
        "https://g1.globo.com/stf-coaf-investigacoes"
      ],
      "pessoas_envolvidas": ["Alexandre de Moraes"],
      "instituicoes_envolvidas": ["STF", "COAF"],
      "pais": "Brasil",
      "prioridade": 1
    },
    {
      "id": 7,
      "titulo": "Congresso debate corte de penduricalhos no judiciário após pressão popular",
      "data_evento": "2025-11-02",
      "data_iso": "2025-11-02T11:20:00.000Z",
      "categoria": "penduricalhos",
      "tags": ["penduricalhos", "justica", "escandalos", "stf"],
      "descricao": "Projeto propõe redução de benefícios extras para magistrados, aumentando polarização entre Poderes.",
      "relevancia": "media",
      "fontes": [
        "https://www.camara.leg.br/noticias/corte-penduricalhos-2025/",
        "https://www.gazetadopovo.com.br/politica/penduricalhos-magistrados"
      ],
      "pessoas_envolvidas": ["Presidente da Câmara"],
      "instituicoes_envolvidas": ["Câmara dos Deputados", "STF"],
      "pais": "Brasil",
      "prioridade": 5
    },
    {
      "id": 8,
      "titulo": "Grupo internacional denuncia censura promovida por governo brasileiro",
      "data_evento": "2025-11-10",
      "data_iso": "2025-11-10T18:00:00.000Z",
      "categoria": "lawfare",
      "tags": ["lawfare", "censura", "soberania", "escandalos", "liberdade de expressão"],
      "descricao": "ONG aponta violações sistemáticas da liberdade de expressão em relatório apresentado à ONU.",
      "relevancia": "alta",
      "fontes": [
        "https://www.hrw.org/denuncia-censura-relatorio-brasil-2025/",
        "https://noticias.uol.com.br/brasil-relatorio-onu-censura"
      ],
      "pessoas_envolvidas": ["Diretor da Human Rights Watch"],
      "instituicoes_envolvidas": ["ONU", "Human Rights Watch"],
      "pais": "Brasil",
      "prioridade": 2
    },
    {
      "id": 9,
      "titulo": "STF absolve deputado acusado de lavagem de dinheiro por suposta insuficiência de provas",
      "data_evento": "2025-11-12",
      "data_iso": "2025-11-12T15:05:00.000Z",
      "categoria": "impunidade",
      "tags": ["impunidade", "stf", "lavagem-de-dinheiro", "decisao-judicial", "justica"],
      "descricao": "Decisão do STF levanta críticas sobre favorecimento de políticos e questiona o combate à impunidade.",
      "relevancia": "media",
      "fontes": [
        "https://politica.estadao.com.br/noticias-deputado-stf-impunidade-2025/",
        "https://www.gazetadopovo.com.br/politica/stf-absolvimento-deputado"
      ],
      "pessoas_envolvidas": ["Deputado José Carvalho"],
      "instituicoes_envolvidas": ["STF"],
      "pais": "Brasil",
      "prioridade": 4
    },
    {
      "id": 10,
      "titulo": "Hackers expõem conversas de ministros do TSE sobre eleições municipais",
      "data_evento": "2025-11-16",
      "data_iso": "2025-11-16T20:00:00.000Z",
      "categoria": "vazatoga",
      "tags": ["vazatoga", "tse", "eleições", "dossie", "escandalos", "liberdade de expressão"],
      "descricao": "Grupo hacker publica diálogos que revelam debates internos sobre estratégias de fiscalização digital das eleições.",
      "relevancia": "alta",
      "fontes": [
        "https://veja.abril.com.br/politica/hackers-conversas-tse-2025/",
        "https://www.uol.com.br/politica/tse-hacker-eleicoes-2025"
      ],
      "pessoas_envolvidas": ["Ministro Raul Araújo"],
      "instituicoes_envolvidas": ["TSE", "PF"],
      "pais": "Brasil",
      "prioridade": 2
    }
  ],
  "total": 10,
  "data_pesquisa": "2025-11-17",
  "periodo": "2025-09-15 a 2025-11-17"
}
